rdpvps_999/__init__.py
rdpvps_999/test.py
suuuuuuuuu_suuuuu-0.0.1.dist-info/LICENSE.txt
suuuuuuuuu_suuuuu-0.0.1.dist-info/METADATA
suuuuuuuuu_suuuuu-0.0.1.dist-info/WHEEL
suuuuuuuuu_suuuuu-0.0.1.dist-info/top_level.txt
suuuuuuuuu_suuuuu-0.0.1.dist-info/RECORD
