Metadata-Version: 2.1
Name: suuuuuuuuu-suuuuu
Version: 0.0.1
Summary: suuuuuuuuuuuu
Author: NeuralNine (Florian Dedov)
Author-email: fiobhfigbhfigbhfgui@gmail.com
Keywords: python,video,stream,video stream,camera stream,sockets
Classifier: Development Status :: 1 - Planning
Classifier: Intended Audience :: Developers
Classifier: Programming Language :: Python :: 3
Classifier: Operating System :: Unix
Classifier: Operating System :: MacOS :: MacOS X
Classifier: Operating System :: Microsoft :: Windows
License-File: LICENSE.txt
Requires-Dist: opencv-python
Requires-Dist: pyautogui
Requires-Dist: pyaudio
